lsutil/__init__.py
lsutil/lsutil.py
lsutil/static/docs/404.html
lsutil/static/docs/index.html
lsutil/static/docs/sitemap.xml
lsutil/static/docs/sitemap.xml.gz
lsutil/static/docs/api/index.html
lsutil/static/docs/assets/images/favicon.png
lsutil/static/docs/assets/javascripts/bundle.8aa65030.min.js
lsutil/static/docs/assets/javascripts/bundle.8aa65030.min.js.map
lsutil/static/docs/assets/stylesheets/main.e8d9bf0c.min.css
lsutil/static/docs/assets/stylesheets/main.e8d9bf0c.min.css.map
lsutil/static/docs/assets/stylesheets/palette.e6a45f82.min.css
lsutil/static/docs/assets/stylesheets/palette.e6a45f82.min.css.map
lsutil/static/docs/dev/index.html
lsutil/static/docs/man/index.html
lsutil/static/docs/search/search_index.json
lsutil-0.0.22.dist-info/LICENSE
lsutil-0.0.22.dist-info/METADATA
lsutil-0.0.22.dist-info/WHEEL
lsutil-0.0.22.dist-info/entry_points.txt
lsutil-0.0.22.dist-info/top_level.txt
lsutil-0.0.22.dist-info/RECORD
