Metadata-Version: 2.1
Name: lsutil
Version: 0.0.22
Summary: Unix ls in Python
Home-page: https://koobedoc.github.io/lsutil/
License: GNU GPLv3
Keywords: unix,ls
Platform: UNKNOWN
License-File: LICENSE
Requires-Dist: rich
